mypythonlib_project/__init__.py
mypythonlib_project/chapter_titles.py
mypythonlib_project/chapter_titles_frpdf.py
mypythonlib_project/clean_text.py
mypythonlib_project/ent_ait_fix.py
mypythonlib_project/fix_lines.py
mypythonlib_project/liaisons.py
mypythonlib_project/main.py
mypythonlib_project/name_correction.py
mypythonlib_project/pdf_2_txt.py
mypythonlib_project/remove_pnum_hilight_title.py
mypythonlib_project/replace_numbers.py
mypythonlib_project/replace_special_chars.py
mypythonlib_project/replace_words.py
mypythonlib_project/split_chapters.py
mypythonlib_project-0.1.4.dist-info/METADATA
mypythonlib_project-0.1.4.dist-info/WHEEL
mypythonlib_project-0.1.4.dist-info/top_level.txt
mypythonlib_project-0.1.4.dist-info/RECORD
