Metadata-Version: 2.1
Name: mypythonlib_project
Version: 0.1.4
Summary: My Python library
Author: Nasim
